cpack/__init__.py
cpack/py.typed
cpack/version.py
cpack-0.1.0a0.dist-info/LICENSE
cpack-0.1.0a0.dist-info/METADATA
cpack-0.1.0a0.dist-info/WHEEL
cpack-0.1.0a0.dist-info/top_level.txt
cpack-0.1.0a0.dist-info/RECORD
